{
  "generated_at": "2026-06-02T23:50:25.893277+00:00",
  "prices": {
    "brent": {
      "name": "Brent Oil",
      "price": 97.4,
      "change": 2.55,
      "formatted_price": "$97.40",
      "formatted_change": "+2.55%",
      "updated_at": "2026-06-02T23:50:25.609077+00:00"
    },
    "gas": {
      "name": "Natural Gas",
      "price": 3.173,
      "change": -0.19,
      "formatted_price": "$3.173",
      "formatted_change": "-0.19%",
      "updated_at": "2026-06-02T23:50:25.721312+00:00"
    },
    "gold": {
      "name": "Gold",
      "price": 4492.9,
      "change": 0.4,
      "formatted_price": "$4493",
      "formatted_change": "+0.40%",
      "updated_at": "2026-06-02T23:50:25.820156+00:00"
    },
    "bitcoin": {
      "name": "Bitcoin",
      "price": 66662.0,
      "change": -6.53,
      "formatted_price": "$66,662",
      "formatted_change": "-6.53%",
      "updated_at": "2026-06-02T23:50:25.893268+00:00"
    }
  }
}