{
  "generated_at": "2026-04-13T21:43:38.578620+00:00",
  "prices": {
    "brent": {
      "name": "Brent Oil",
      "price": 98.11,
      "change": 3.06,
      "formatted_price": "$98.11",
      "formatted_change": "+3.06%",
      "updated_at": "2026-04-13T21:43:38.010890+00:00"
    },
    "gas": {
      "name": "Natural Gas",
      "price": 2.627,
      "change": -0.79,
      "formatted_price": "$2.627",
      "formatted_change": "-0.79%",
      "updated_at": "2026-04-13T21:43:38.156613+00:00"
    },
    "gold": {
      "name": "Gold",
      "price": 4766.6,
      "change": -0.43,
      "formatted_price": "$4767",
      "formatted_change": "-0.43%",
      "updated_at": "2026-04-13T21:43:38.379163+00:00"
    },
    "bitcoin": {
      "name": "Bitcoin",
      "price": 73284.39,
      "change": 3.58,
      "formatted_price": "$73,284",
      "formatted_change": "+3.58%",
      "updated_at": "2026-04-13T21:43:38.578599+00:00"
    }
  }
}