{
  "generated_at": "2026-03-13T13:58:36.938989+00:00",
  "prices": {
    "brent": {
      "name": "Brent Oil",
      "price": 99.57,
      "change": -0.89,
      "formatted_price": "$99.57",
      "formatted_change": "-0.89%",
      "updated_at": "2026-03-13T13:58:36.630409+00:00"
    },
    "gas": {
      "name": "Natural Gas",
      "price": 3.148,
      "change": -2.63,
      "formatted_price": "$3.148",
      "formatted_change": "-2.63%",
      "updated_at": "2026-03-13T13:58:36.688383+00:00"
    },
    "gold": {
      "name": "Gold",
      "price": 5119.0,
      "change": 0.06,
      "formatted_price": "$5119",
      "formatted_change": "+0.06%",
      "updated_at": "2026-03-13T13:58:36.884996+00:00"
    },
    "bitcoin": {
      "name": "Bitcoin",
      "price": 73580.6,
      "change": 4.38,
      "formatted_price": "$73,581",
      "formatted_change": "+4.38%",
      "updated_at": "2026-03-13T13:58:36.938980+00:00"
    }
  }
}