{
  "generated_at": "2026-06-28T12:37:49.884193+00:00",
  "prices": {
    "brent": {
      "name": "Brent Oil",
      "price": 72.6,
      "change": 0.85,
      "formatted_price": "$72.60",
      "formatted_change": "+0.85%",
      "updated_at": "2026-06-28T12:37:49.684454+00:00"
    },
    "gas": {
      "name": "Natural Gas",
      "price": 3.279,
      "change": 1.49,
      "formatted_price": "$3.279",
      "formatted_change": "+1.49%",
      "updated_at": "2026-06-28T12:37:49.748005+00:00"
    },
    "gold": {
      "name": "Gold",
      "price": 4096.3,
      "change": 0.43,
      "formatted_price": "$4096",
      "formatted_change": "+0.43%",
      "updated_at": "2026-06-28T12:37:49.812614+00:00"
    },
    "bitcoin": {
      "name": "Bitcoin",
      "price": 60193.27,
      "change": 0.42,
      "formatted_price": "$60,193",
      "formatted_change": "+0.42%",
      "updated_at": "2026-06-28T12:37:49.884175+00:00"
    }
  }
}