{
  "generated_at": "2026-03-11T11:24:57.476790+00:00",
  "prices": {
    "brent": {
      "name": "Brent Oil",
      "price": 86.16,
      "change": -1.87,
      "formatted_price": "$86.16",
      "formatted_change": "-1.87%",
      "updated_at": "2026-03-11T11:24:57.318626+00:00"
    },
    "gas": {
      "name": "Natural Gas",
      "price": 3.052,
      "change": 1.06,
      "formatted_price": "$3.052",
      "formatted_change": "+1.06%",
      "updated_at": "2026-03-11T11:24:57.369043+00:00"
    },
    "gold": {
      "name": "Gold",
      "price": 5195.2,
      "change": -0.66,
      "formatted_price": "$5195",
      "formatted_change": "-0.66%",
      "updated_at": "2026-03-11T11:24:57.423719+00:00"
    },
    "bitcoin": {
      "name": "Bitcoin",
      "price": 69535.1,
      "change": -0.56,
      "formatted_price": "$69,535",
      "formatted_change": "-0.56%",
      "updated_at": "2026-03-11T11:24:57.476768+00:00"
    }
  }
}