{
  "generated_at": "2026-06-29T07:58:21.750435+00:00",
  "prices": {
    "brent": {
      "name": "Brent Oil",
      "price": 72.94,
      "change": 0.47,
      "formatted_price": "$72.94",
      "formatted_change": "+0.47%",
      "updated_at": "2026-06-29T07:58:21.533833+00:00"
    },
    "gas": {
      "name": "Natural Gas",
      "price": 3.257,
      "change": -0.67,
      "formatted_price": "$3.257",
      "formatted_change": "-0.67%",
      "updated_at": "2026-06-29T07:58:21.599012+00:00"
    },
    "gold": {
      "name": "Gold",
      "price": 4077.0,
      "change": -0.47,
      "formatted_price": "$4077",
      "formatted_change": "-0.47%",
      "updated_at": "2026-06-29T07:58:21.680081+00:00"
    },
    "bitcoin": {
      "name": "Bitcoin",
      "price": 59950.43,
      "change": 0.7,
      "formatted_price": "$59,950",
      "formatted_change": "+0.70%",
      "updated_at": "2026-06-29T07:58:21.750418+00:00"
    }
  }
}